[
  {
    "id": "CON-1755718774480",
    "contractNo": "TC-1755718766747",
    "contractDate": "2025-08-20",
    "property": "LT-C38",
    "unitCode": "101",
    "roomCode": "",
    "partitionCode": "",
    "tenantCode": "T001",
    "tenantName": "Md Ripon Ahmed",
    "mobile": "0509231340",
    "email": "ripondxn@gmail.com",
    "address": "Village : Rahut Hati , Post office : Hasnabad",
    "startDate": "2025-08-20",
    "endDate": "2025-09-19",
    "totalRent": 55000,
    "paymentMode": "cash",
    "status": "New",
    "terminationDate": "",
    "rentBasedOn": "Monthly",
    "paymentFrequency": "Monthly",
    "numberOfPayments": 2,
    "gracePeriod": 0,
    "paymentSchedule": [
      {
        "installment": 1,
        "dueDate": "2025-08-20",
        "amount": 27500,
        "status": "unpaid",
        "chequeNo": "123456",
        "bankName": "ADCB"
      },
      {
        "installment": 2,
        "dueDate": "2025-09-20",
        "amount": 27500,
        "status": "unpaid",
        "chequeNo": "123457",
        "bankName": "ADCB"
      }
    ],
    "terms": "",
    "tawtheeqRegistrationNo": "12012445",
    "tawtheeqStatus": "Registered",
    "tawtheeqRegistrationDate": "2025-08-21"
  },
  {
    "id": "CON-1755761251503",
    "contractNo": "TC-1755761192274",
    "contractDate": "2025-08-22",
    "property": "LT-C38",
    "unitCode": "102",
    "roomCode": "",
    "partitionCode": "",
    "tenantCode": "T002",
    "tenantName": "Monju Begum",
    "mobile": "01731627179",
    "email": "ripondxn@gmail.com",
    "address": "Village : Rahut Hati , Post office : Hasnabad",
    "startDate": "2025-08-22",
    "endDate": "2026-01-20",
    "totalRent": 75000,
    "paymentMode": "cash",
    "status": "New",
    "terminationDate": "",
    "rentBasedOn": "Monthly",
    "paymentFrequency": "Quarterly",
    "numberOfPayments": 3,
    "gracePeriod": 0,
    "paymentSchedule": [
      {
        "installment": 1,
        "dueDate": "2025-08-22",
        "amount": 25000,
        "status": "paid",
        "chequeNo": "2258765",
        "bankName": "NBD"
      },
      {
        "installment": 2,
        "dueDate": "2025-11-22",
        "amount": 25000,
        "status": "paid",
        "chequeNo": "256878",
        "bankName": "NBD"
      },
      {
        "installment": 3,
        "dueDate": "2026-02-22",
        "amount": 25000,
        "status": "paid",
        "chequeNo": "65879978",
        "bankName": "NBD"
      }
    ],
    "terms": "",
    "tawtheeqRegistrationNo": "",
    "tawtheeqStatus": "Not Registered",
    "tawtheeqRegistrationDate": ""
  }
]